coreframe/__init__.py
coreframe/coreframe.py
coreframe/from_csv.py
coreframe/from_nc.py
cf_test_upload-0.0.1.dist-info/METADATA
cf_test_upload-0.0.1.dist-info/WHEEL
cf_test_upload-0.0.1.dist-info/top_level.txt
cf_test_upload-0.0.1.dist-info/RECORD
