Metadata-Version: 2.1
Name: cf-test-upload
Version: 0.0.1
Author: MetaEarth Lab
Author-email: 
Keywords: python
Requires-Dist: numpy
Requires-Dist: h5py
Requires-Dist: pytest
Requires-Dist: pytest-xdist
